<?xml version="1.0" encoding="UTF-8" standalone="no"?>
<DIAGRAMA ID="1" TIPO="tpConceitual" UniversalUnicID="8265-37-7ABA-6E-5517-67-6A">
<InfoDiagrama ID="1">
<Versao Valor="3.2.0"/>
<Autores/>
<Observacao/>
<Width Valor="4096"/>
<Height Valor="4096"/>
<Alinhamento_v Valor="50"/>
<Alinhamento_h Valor="60"/>
<Zoom Valor="100"/>
<Fonte Estilo="1" Nome="Arial" Tamanho="12"/>
<Localizacao Left="0" Top="100"/>
<Realce Valor="false"/>
</InfoDiagrama>
<Entidade ID="218">
<Bounds Height="58" Left="224" Top="237" Width="120"/>
<DisablePainted Valor="false"/>
<Texto>Engenheiro</Texto>
<Observacao/>
<Dicionario/>
<Fonte Estilo="1" Nome="Arial" Tamanho="12"/>
<Ancorado Valor="false"/>
<AtributosOcultos Valor=""/>
</Entidade>
<Entidade ID="219">
<Bounds Height="58" Left="723" Top="236" Width="120"/>
<DisablePainted Valor="false"/>
<Texto>Projeto</Texto>
<Observacao/>
<Dicionario/>
<Fonte Estilo="1" Nome="Arial" Tamanho="12"/>
<Ancorado Valor="false"/>
<AtributosOcultos Valor=""/>
</Entidade>
<Entidade ID="243">
<Bounds Height="58" Left="470" Top="473" Width="120"/>
<DisablePainted Valor="false"/>
<Texto>Funcionário</Texto>
<Observacao/>
<Dicionario/>
<Fonte Estilo="1" Nome="Arial" Tamanho="12"/>
<Ancorado Valor="false"/>
<AtributosOcultos Valor=""/>
</Entidade>
<Relacionamento ID="246">
<Bounds Height="50" Left="466" Top="364" Width="150"/>
<DisablePainted Valor="false"/>
<Texto>Relacionamento_1</Texto>
<Observacao/>
<Dicionario/>
<Fonte Estilo="1" Nome="Arial" Tamanho="12"/>
<Ancorado Valor="false"/>
</Relacionamento>
<Relacionamento ID="247">
<Bounds Height="50" Left="466" Top="241" Width="150"/>
<DisablePainted Valor="false"/>
<Texto>Relacionamento_2</Texto>
<Observacao/>
<Dicionario/>
<Fonte Estilo="1" Nome="Arial" Tamanho="12"/>
<Ancorado Valor="false"/>
</Relacionamento>
<Ligacao ID="252">
<DisablePainted Valor="false"/>
<Tag LinhaMestre="-1"/>
<Dashed Valor="false"/>
<Ancorado Valor="false"/>
<TemSetaPontaA Valor="false"/>
<TemSetaPontaB Valor="false"/>
<SetaAberta Valor="true"/>
<SetaLargura Valor="10"/>
<Inteligente Valor="true"/>
<Largura Valor="1"/>
<Ligacoes PontaA="243" PontaB="246"/>
<Pontos>
<Ponto Left="538" Top="469"/>
<Ponto Left="538" Top="440"/>
<Ponto Left="538" Top="440"/>
<Ponto Left="538" Top="411"/>
</Pontos>
<Cardinalidade ID="253">
<Bounds Height="15" Left="505" Top="450" Width="35"/>
<DisablePainted Valor="false"/>
<Texto>Cardinalidade_1</Texto>
<Observacao/>
<Dicionario/>
<Fonte Estilo="1" Nome="Arial" Tamanho="12"/>
<Ancorado Valor="false"/>
<TamanhoAutmatico Valor="true"/>
<Card Valor="2"/>
<MovimentacaoManual Valor="false"/>
<Papel Valor=""/>
</Cardinalidade>
</Ligacao>
<Ligacao ID="254">
<DisablePainted Valor="false"/>
<Tag LinhaMestre="-1"/>
<Dashed Valor="false"/>
<Ancorado Valor="false"/>
<TemSetaPontaA Valor="false"/>
<TemSetaPontaB Valor="false"/>
<SetaAberta Valor="true"/>
<SetaLargura Valor="10"/>
<Inteligente Valor="true"/>
<Largura Valor="1"/>
<Ligacoes PontaA="218" PontaB="247"/>
<Pontos>
<Ponto Left="296" Top="292"/>
<Ponto Left="296" Top="302"/>
<Ponto Left="513" Top="302"/>
<Ponto Left="513" Top="280"/>
</Pontos>
<Cardinalidade ID="255">
<Bounds Height="15" Left="263" Top="302" Width="35"/>
<DisablePainted Valor="false"/>
<Texto>Cardinalidade_2</Texto>
<Observacao/>
<Dicionario/>
<Fonte Estilo="1" Nome="Arial" Tamanho="12"/>
<Ancorado Valor="false"/>
<TamanhoAutmatico Valor="true"/>
<Card Valor="0"/>
<MovimentacaoManual Valor="false"/>
<Papel Valor=""/>
</Cardinalidade>
</Ligacao>
<Ligacao ID="256">
<DisablePainted Valor="false"/>
<Tag LinhaMestre="-1"/>
<Dashed Valor="false"/>
<Ancorado Valor="false"/>
<TemSetaPontaA Valor="false"/>
<TemSetaPontaB Valor="false"/>
<SetaAberta Valor="true"/>
<SetaLargura Valor="10"/>
<Inteligente Valor="true"/>
<Largura Valor="1"/>
<Ligacoes PontaA="247" PontaB="219"/>
<Pontos>
<Ponto Left="538" Top="238"/>
<Ponto Left="538" Top="228"/>
<Ponto Left="666" Top="228"/>
<Ponto Left="666" Top="301"/>
<Ponto Left="759" Top="301"/>
<Ponto Left="759" Top="291"/>
</Pontos>
<Cardinalidade ID="257">
<Bounds Height="15" Left="699" Top="304" Width="35"/>
<DisablePainted Valor="false"/>
<Texto>Cardinalidade_3</Texto>
<Observacao/>
<Dicionario/>
<Fonte Estilo="1" Nome="Arial" Tamanho="12"/>
<Ancorado Valor="false"/>
<TamanhoAutmatico Valor="true"/>
<Card Valor="2"/>
<MovimentacaoManual Valor="true"/>
<Papel Valor=""/>
</Cardinalidade>
</Ligacao>
<Ligacao ID="260">
<DisablePainted Valor="false"/>
<Tag LinhaMestre="-1"/>
<Dashed Valor="false"/>
<Ancorado Valor="false"/>
<TemSetaPontaA Valor="false"/>
<TemSetaPontaB Valor="false"/>
<SetaAberta Valor="true"/>
<SetaLargura Valor="10"/>
<Inteligente Valor="true"/>
<Largura Valor="1"/>
<Ligacoes PontaA="246" PontaB="219"/>
<Pontos>
<Ponto Left="588" Top="378"/>
<Ponto Left="825" Top="378"/>
<Ponto Left="825" Top="291"/>
</Pontos>
<Cardinalidade ID="261">
<Bounds Height="15" Left="791" Top="301" Width="35"/>
<DisablePainted Valor="false"/>
<Texto>Cardinalidade_4</Texto>
<Observacao/>
<Dicionario/>
<Fonte Estilo="1" Nome="Arial" Tamanho="12"/>
<Ancorado Valor="false"/>
<TamanhoAutmatico Valor="true"/>
<Card Valor="2"/>
<MovimentacaoManual Valor="true"/>
<Papel Valor=""/>
</Cardinalidade>
</Ligacao>
</DIAGRAMA>
